{
	"configurations" : 
	[
		{
			"directories" : 
			[
				{
					"build" : ".",
					"jsonFile" : "directory-.-Debug-d0094a50bb2071803777.json",
					"minimumCMakeVersion" : 
					{
						"string" : "3.29"
					},
					"projectIndex" : 0,
					"source" : ".",
					"targetIndexes" : 
					[
						0
					]
				}
			],
			"name" : "Debug",
			"projects" : 
			[
				{
					"directoryIndexes" : 
					[
						0
					],
					"name" : "carRentalCommandLine",
					"targetIndexes" : 
					[
						0
					]
				}
			],
			"targets" : 
			[
				{
					"directoryIndex" : 0,
					"id" : "carRentalCommandLine::@6890427a1f51a3e7e1df",
					"jsonFile" : "target-carRentalCommandLine-Debug-a103f675db298e82aca4.json",
					"name" : "carRentalCommandLine",
					"projectIndex" : 0
				}
			]
		}
	],
	"kind" : "codemodel",
	"paths" : 
	{
		"build" : "C:/Users/ingvi/ikt103_eksamen/Oline_Ingvild_IKT103Exam/carRentalCommandLine/cmake-build-debug",
		"source" : "C:/Users/ingvi/ikt103_eksamen/Oline_Ingvild_IKT103Exam/carRentalCommandLine"
	},
	"version" : 
	{
		"major" : 2,
		"minor" : 7
	}
}
